pypdp/__init__.py
pypdp/env.py
pypdp/engine/__init__.py
pypdp/engine/delivery.py
pypdp/engine/depot.py
pypdp/engine/manager.py
pypdp/engine/pickup.py
pypdp/engine/status.py
pypdp/engine/vehicle.py
pypdp/utils/__init__.py
pypdp/utils/action_space.py
pypdp/utils/generate_coords.py
pypdp/utils/generate_problem.py
pypdp/utils/observations.py
pypdp/utils/rewards.py
pypdp/utils/visualization.py
pypdp-0.0.0.0.dist-info/METADATA
pypdp-0.0.0.0.dist-info/WHEEL
pypdp-0.0.0.0.dist-info/top_level.txt
pypdp-0.0.0.0.dist-info/RECORD
